django_cardano/__init__.py
django_cardano/cli.py
django_cardano/exceptions.py
django_cardano/fields.py
django_cardano/models.py
django_cardano/settings.py
django_cardano/shortcuts.py
django_cardano/storage.py
django_cardano/tests.py
django_cardano/util.py
django_cardano/validators.py
django_cardano/migrations/0001_initial.py
django_cardano/migrations/__init__.py
django_cardano-1.33.0.dist-info/LICENSE
django_cardano-1.33.0.dist-info/METADATA
django_cardano-1.33.0.dist-info/WHEEL
django_cardano-1.33.0.dist-info/top_level.txt
django_cardano-1.33.0.dist-info/RECORD
